PyEasyUtils/__init__.py
PyEasyUtils/cmd.py
PyEasyUtils/config.py
PyEasyUtils/database.py
PyEasyUtils/env.py
PyEasyUtils/log.py
PyEasyUtils/math.py
PyEasyUtils/overload.py
PyEasyUtils/path.py
PyEasyUtils/process.py
PyEasyUtils/text.py
PyEasyUtils/utils.py
PyEasyUtils/web.py
pyeasyutils-0.3.6.dist-info/licenses/LICENSE
pyeasyutils-0.3.6.dist-info/METADATA
pyeasyutils-0.3.6.dist-info/WHEEL
pyeasyutils-0.3.6.dist-info/top_level.txt
pyeasyutils-0.3.6.dist-info/RECORD
