Metadata-Version: 2.4
Name: PyEasyUtils
Version: 0.3.6
Summary: A simple python util library
Home-page: https://github.com/Spr-Aachen/PyEasyUtils
Author: Spr_Aachen
Author-email: 2835946988@qq.com
License: MIT
Project-URL: Source Code, https://github.com/Spr-Aachen/PyEasyUtils
Project-URL: Bug Tracker, https://github.com/Spr-Aachen/PyEasyUtils/issues
Classifier: Operating System :: OS Independent
Classifier: Programming Language :: Python :: 3
Classifier: License :: OSI Approved :: MIT License
License-File: LICENSE
Requires-Dist: psutil
Requires-Dist: loguru
Requires-Dist: polars
Requires-Dist: sqlalchemy
Requires-Dist: PyGithub
Dynamic: author
Dynamic: author-email
Dynamic: classifier
Dynamic: description
Dynamic: description-content-type
Dynamic: home-page
Dynamic: license
Dynamic: license-file
Dynamic: project-url
Dynamic: requires-dist
Dynamic: summary
